ipaytools/__init__.py
ipaytools/core.py
ipaytools/core_enhanced.py
ipaytools-1.0.0.dist-info/licenses/LICENSE
ipaytools-1.0.0.dist-info/METADATA
ipaytools-1.0.0.dist-info/WHEEL
ipaytools-1.0.0.dist-info/entry_points.txt
ipaytools-1.0.0.dist-info/top_level.txt
ipaytools-1.0.0.dist-info/RECORD
